{"pageProps":{"posts":[{"slug":"cursoreact---introducao","title":"Conheça o ReactJS","excerpt":"O React, lançado em 2013, é uma biblioteca JavaScript de código aberto, fundamental para criação de aplicações front-end.","updatedAt":"29/03/2022"},{"slug":"cursoreact-native---fundamentos","title":"Conheça React Native","excerpt":"Criado pelo Facebook em 2015 sobre a licença MIT, o React Native é um Framework para desenvolvimento de aplicativos móveis multiplataforma.","updatedAt":"29/03/2022"}]},"__N_SSG":true}